nop_mcp/__init__.py
nop_mcp/server.py
nop_mcp-0.1.1.dist-info/METADATA
nop_mcp-0.1.1.dist-info/WHEEL
nop_mcp-0.1.1.dist-info/entry_points.txt
nop_mcp-0.1.1.dist-info/licenses/LICENSE
nop_mcp-0.1.1.dist-info/RECORD
