Metadata-Version: 2.4
Name: nop-mcp
Version: 0.1.1
Summary: A no-operation MCP server that provides an empty tools list
Project-URL: Homepage, https://github.com/yourusername/nop-mcp
Project-URL: Documentation, https://github.com/yourusername/nop-mcp#readme
Project-URL: Repository, https://github.com/yourusername/nop-mcp.git
Project-URL: Bug Tracker, https://github.com/yourusername/nop-mcp/issues
Author-email: Your Name <your.email@example.com>
Maintainer-email: Your Name <your.email@example.com>
License: MIT
License-File: LICENSE
Keywords: ai,mcp,model-context-protocol,server,tools
Classifier: Development Status :: 3 - Alpha
Classifier: Intended Audience :: Developers
Classifier: License :: OSI Approved :: MIT License
Classifier: Programming Language :: Python :: 3
Classifier: Programming Language :: Python :: 3.10
Classifier: Programming Language :: Python :: 3.11
Classifier: Programming Language :: Python :: 3.12
Classifier: Programming Language :: Python :: 3.13
Classifier: Topic :: Scientific/Engineering :: Artificial Intelligence
Classifier: Topic :: Software Development :: Libraries :: Python Modules
Requires-Python: >=3.10
Requires-Dist: mcp>=1.2.0
Provides-Extra: dev
Requires-Dist: black; extra == 'dev'
Requires-Dist: build; extra == 'dev'
Requires-Dist: flake8; extra == 'dev'
Requires-Dist: pytest; extra == 'dev'
Requires-Dist: twine; extra == 'dev'
